spihole/__init__.py
spihole/__main__.py
spihole/_version.py
spihole/capture.py
spihole/cli.py
spihole/display.py
spihole/hub.py
spihole/keypad.py
spihole/lcd/__init__.py
spihole/lcd/config.py
spihole/lcd/fake_spi.py
spihole-0.0.4.dist-info/AUTHORS.rst
spihole-0.0.4.dist-info/LICENSE
spihole-0.0.4.dist-info/METADATA
spihole-0.0.4.dist-info/WHEEL
spihole-0.0.4.dist-info/entry_points.txt
spihole-0.0.4.dist-info/top_level.txt
spihole-0.0.4.dist-info/RECORD
