Metadata-Version: 2.1
Name: spihole
Version: 0.0.4
Summary: Operate a raspberrypi powered peephole camera
Home-page: https://github.com/zoloft/python-spihole
Author: zoloft
Author-email: zoloft@orcod.io
License: MIT
Project-URL: Documentation, https://python-spihole.readthedocs.io/
Project-URL: Changelog, https://python-spihole.readthedocs.io/en/latest/changelog.html
Project-URL: Issue Tracker, https://github.com/zoloft/python-spihole/issues
Keywords: raspberry,waveshare,camera,spyhole,peephole,automation
Platform: UNKNOWN
Classifier: Development Status :: 5 - Production/Stable
Classifier: Intended Audience :: Developers
Classifier: License :: OSI Approved :: MIT License
Classifier: Operating System :: Unix
Classifier: Operating System :: POSIX
Classifier: Programming Language :: Python
Classifier: Programming Language :: Python :: 3
Classifier: Programming Language :: Python :: 3 :: Only
Classifier: Programming Language :: Python :: 3.6
Classifier: Programming Language :: Python :: 3.7
Classifier: Programming Language :: Python :: 3.8
Classifier: Programming Language :: Python :: 3.9
Classifier: Programming Language :: Python :: 3.10
Classifier: Programming Language :: Python :: Implementation :: CPython
Classifier: Programming Language :: Python :: Implementation :: PyPy
Classifier: Topic :: Utilities
License-File: LICENSE
License-File: AUTHORS.rst
Requires-Dist: click
Requires-Dist: numpy
Requires-Dist: Pillow
Requires-Dist: fake-rpi ; platform_system != "Linux" or platform_machine != "armv6l"
Requires-Dist: picamera ; platform_system == "Linux" and platform_machine == "armv6l"
Requires-Dist: spidev ; platform_system == "Linux" and platform_machine == "armv6l"
Requires-Dist: RPi.GPIO ; platform_system == "Linux" and platform_machine == "armv6l"
